video_to_ascii/__init__.py
video_to_ascii/cli.py
video_to_ascii/player.py
video_to_ascii/video_engine.py
video_to_ascii/render_strategy/__init__.py
video_to_ascii/render_strategy/ascii_bw_strategy.py
video_to_ascii/render_strategy/ascii_color_filled_strategy.py
video_to_ascii/render_strategy/ascii_color_strategy.py
video_to_ascii/render_strategy/ascii_strategy.py
video_to_ascii/render_strategy/image_processor.py
video_to_ascii/render_strategy/image_processor_win.py
video_to_ascii/render_strategy/render_strategy.py
video_to_ascii-1.3.1.dist-info/licenses/LICENSE
video_to_ascii-1.3.1.dist-info/METADATA
video_to_ascii-1.3.1.dist-info/WHEEL
video_to_ascii-1.3.1.dist-info/entry_points.txt
video_to_ascii-1.3.1.dist-info/top_level.txt
video_to_ascii-1.3.1.dist-info/RECORD
