Metadata-Version: 2.4
Name: video-to-ascii
Version: 1.3.1
Summary: It is a simple python package to play videos in the terminal
Author-email: Joel Ibaceta <mail@joelibaceta.com>
Maintainer-email: Joel Ibaceta <mail@joelibaceta.com>
License-Expression: MIT
Project-URL: Homepage, https://github.com/joelibaceta/video-to-ascii
Project-URL: Repository, https://github.com/joelibaceta/video-to-ascii
Project-URL: Issues, https://github.com/joelibaceta/video-to-ascii/issues
Project-URL: Documentation, https://github.com/joelibaceta/video-to-ascii#readme
Keywords: video,ascii,terminal,opencv
Classifier: Development Status :: 4 - Beta
Classifier: Intended Audience :: Developers
Classifier: Operating System :: OS Independent
Classifier: Programming Language :: Python :: 3
Classifier: Programming Language :: Python :: 3.8
Classifier: Programming Language :: Python :: 3.9
Classifier: Programming Language :: Python :: 3.10
Classifier: Programming Language :: Python :: 3.11
Classifier: Programming Language :: Python :: 3.12
Classifier: Topic :: Multimedia :: Video
Classifier: Topic :: Terminals
Requires-Python: >=3.8
License-File: LICENSE
Requires-Dist: opencv-python>=4.5.0
Requires-Dist: xtermcolor>=2.0.0
Requires-Dist: ffmpeg-python>=0.2.0
Provides-Extra: audio
Requires-Dist: pyaudio>=0.2.11; extra == "audio"
Provides-Extra: dev
Requires-Dist: pytest>=6.0; extra == "dev"
Requires-Dist: black; extra == "dev"
Requires-Dist: flake8; extra == "dev"
Requires-Dist: mypy; extra == "dev"
Provides-Extra: all
Requires-Dist: video-to-ascii[audio]; extra == "all"
Dynamic: license-file
